pymdp/__init__.py
pymdp/agent.py
pymdp/control.py
pymdp/default_models.py
pymdp/inference.py
pymdp/learning.py
pymdp/maths.py
pymdp/utils.py
pymdp/algos/__init__.py
pymdp/algos/fpi.py
pymdp/algos/mmp.py
pymdp/algos/mmp_old.py
pymdp/envs/__init__.py
pymdp/envs/env.py
pymdp/envs/grid_worlds.py
pymdp/envs/mdp_search_env.py
pymdp/envs/tmaze.py
pymdp/envs/visual_foraging.py
test_inferactively_pymdp-0.0.3.dist-info/LICENSE
test_inferactively_pymdp-0.0.3.dist-info/METADATA
test_inferactively_pymdp-0.0.3.dist-info/WHEEL
test_inferactively_pymdp-0.0.3.dist-info/top_level.txt
test_inferactively_pymdp-0.0.3.dist-info/RECORD
