Metadata-Version: 2.1
Name: test-inferactively-pymdp
Version: 0.0.3
Summary: A Python package for solving Markov Decision Processes with Active Inference
Home-page: https://github.com/infer-actively/pymdp
Author: infer-actively
Author-email: conor.heins@gmail.com
License: MIT
Keywords: artificial intelligence,active inference,free energy principleinformation theory,decision-making,MDP,Markov Decision Process,Bayesian inference,variational inference,reinforcement learning
Platform: UNKNOWN
Classifier: Development Status :: 4 - Beta
Classifier: Intended Audience :: Developers
Classifier: Topic :: Scientific/Engineering :: Artificial Intelligence
Classifier: License :: OSI Approved :: MIT License
Classifier: Programming Language :: Python :: 3.7
Requires-Python: >3.7
License-File: LICENSE
Requires-Dist: attrs (>=20.3.0)
Requires-Dist: cycler (>=0.10.0)
Requires-Dist: iniconfig (>=1.1.1)
Requires-Dist: kiwisolver (>=1.3.1)
Requires-Dist: matplotlib (>=3.1.3)
Requires-Dist: nose (>=1.3.7)
Requires-Dist: numpy (>=1.19.5)
Requires-Dist: openpyxl (>=3.0.7)
Requires-Dist: packaging (>=20.8)
Requires-Dist: pandas (>=1.2.4)
Requires-Dist: Pillow (>=8.2.0pluggy>=0.13.1)
Requires-Dist: py (>=1.10.0)
Requires-Dist: pyparsing (>=2.4.7)
Requires-Dist: pytest (>=6.2.1)
Requires-Dist: python-dateutil (>=2.8.1)
Requires-Dist: pytz (>=2020.5)
Requires-Dist: scipy (>=1.6.0)
Requires-Dist: seaborn (>=0.11.1)
Requires-Dist: six (>=1.15.0)
Requires-Dist: toml (>=0.10.2)
Requires-Dist: typing-extensions (>=3.7.4.3)
Requires-Dist: xlsxwriter (>=1.4.3)
